gstorm/BaseGraphQLType.py
gstorm/GraphQLEnum.py
gstorm/GraphQLType.py
gstorm/MutationBuilder.py
gstorm/QueryBuilder.py
gstorm/QueryParser.py
gstorm/__init__.py
gstorm/__version__.py
gstorm/_mutation_runners.py
gstorm/enums.py
gstorm/cli/__init__.py
gstorm/cli/__main__.py
gstorm/cli/scripts/__init__.py
gstorm/cli/scripts/build_classes.py
gstorm/cli/scripts/cleanup.py
gstorm/cli/scripts/utils.py
gstorm/cli/scripts/validate_schema.py
gstorm/helpers/Logging.py
gstorm/helpers/__init__.py
gstorm/helpers/date_helpers.py
gstorm/helpers/gql.py
gstorm/helpers/gql_schema_helpers.py
gstorm/helpers/os_helpers.py
gstorm/helpers/str_handling.py
gstorm/helpers/typing_helpers.py
gstorm-0.12.4.dist-info/METADATA
gstorm-0.12.4.dist-info/WHEEL
gstorm-0.12.4.dist-info/entry_points.txt
gstorm-0.12.4.dist-info/top_level.txt
gstorm-0.12.4.dist-info/RECORD
