Metadata-Version: 2.1
Name: gstorm
Version: 0.12.4
Summary: GraphQL ORM for python (based on pygqlc)
Home-page: https://github.com/valiot/python-gstorm
Author: Valiot
Author-email: hiring@valiot.io
Keywords: gstorm,orm,graphql,gql
Requires-Dist: attrs (<20.0,>=19.3.0)
Requires-Dist: click (<8.0,>=7.1.2)
Requires-Dist: colorama (<0.5,>=0.4)
Requires-Dist: inflect (<6.0,>=5.3.0)
Requires-Dist: pydash (<6.0,>=5.0)
Requires-Dist: pygqlc (<4.0.0,>=3.0.1)
Requires-Dist: python-dateutil (<3.0,>=2.8.2)
Requires-Dist: pytz (==2022.2.1)
Requires-Dist: termcolor (<3.0,>=2.0.1)
Requires-Dist: tzlocal (<5.0,>=4.2)
